buckpy/__init__.py
buckpy/buckpy.py
buckpy/buckpy_gui.py
buckpy/buckpy_postprocessing.py
buckpy/buckpy_preprocessing.py
buckpy/buckpy_solver.py
buckpy/buckpy_variables.py
buckpy/buckpy_visualisation.py
buckpy/_static/logo.png
buckpy/_static/logo.svg
buckpy-0.1.3.dist-info/licenses/LICENSE
buckpy-0.1.3.dist-info/METADATA
buckpy-0.1.3.dist-info/WHEEL
buckpy-0.1.3.dist-info/entry_points.txt
buckpy-0.1.3.dist-info/top_level.txt
buckpy-0.1.3.dist-info/RECORD
