Metadata-Version: 2.4
Name: buckpy
Version: 0.1.3
Summary: BuckPy: Lateral buckling formation algorithm
Home-page: https://github.com/Xodus-Group/BuckPy
Author: ismael-ripoll
License: GPL-3.0-or-later
Project-URL: Documentation, https://buckpy-org.github.io/
Project-URL: Source, https://github.com/Xodus-Group/BuckPy
Project-URL: Tracker, https://github.com/Xodus-Group/BuckPy/issues
Keywords: pipelines,buckling,engineering,reliability,simulation
Classifier: Programming Language :: Python :: 3
Classifier: Programming Language :: Python :: 3.9
Classifier: License :: OSI Approved :: GNU General Public License v3 (GPLv3)
Classifier: Operating System :: OS Independent
Requires-Python: >=3.9
License-File: LICENSE
Requires-Dist: matplotlib==3.8.3
Requires-Dist: multiprocess==0.70.16
Requires-Dist: numba==0.59.0
Requires-Dist: numpy==1.26.4
Requires-Dist: openpyxl==3.1.5
Requires-Dist: pandas==2.2.1
Requires-Dist: scipy==1.12.0
Requires-Dist: xlrd==2.0.1
Requires-Dist: XlsxWriter==3.2.0
Dynamic: author
Dynamic: classifier
Dynamic: description
Dynamic: description-content-type
Dynamic: home-page
Dynamic: keywords
Dynamic: license
Dynamic: license-file
Dynamic: project-url
Dynamic: requires-dist
Dynamic: requires-python
Dynamic: summary
